requests_oauthlib-stubs/METADATA.toml
requests_oauthlib-stubs/__init__.pyi
requests_oauthlib-stubs/oauth1_auth.pyi
requests_oauthlib-stubs/oauth1_session.pyi
requests_oauthlib-stubs/oauth2_auth.pyi
requests_oauthlib-stubs/oauth2_session.pyi
requests_oauthlib-stubs/py.typed
requests_oauthlib-stubs/compliance_fixes/__init__.pyi
requests_oauthlib-stubs/compliance_fixes/douban.pyi
requests_oauthlib-stubs/compliance_fixes/ebay.pyi
requests_oauthlib-stubs/compliance_fixes/facebook.pyi
requests_oauthlib-stubs/compliance_fixes/fitbit.pyi
requests_oauthlib-stubs/compliance_fixes/instagram.pyi
requests_oauthlib-stubs/compliance_fixes/mailchimp.pyi
requests_oauthlib-stubs/compliance_fixes/plentymarkets.pyi
requests_oauthlib-stubs/compliance_fixes/slack.pyi
requests_oauthlib-stubs/compliance_fixes/weibo.pyi
types_requests_oauthlib-2.0.0.20250516.dist-info/licenses/LICENSE
types_requests_oauthlib-2.0.0.20250516.dist-info/METADATA
types_requests_oauthlib-2.0.0.20250516.dist-info/WHEEL
types_requests_oauthlib-2.0.0.20250516.dist-info/top_level.txt
types_requests_oauthlib-2.0.0.20250516.dist-info/RECORD
